LICENSE
README.md
pdf_microarray/__init__.py
pdf_microarray/cli.py
pdf_microarray/pdf_extract.py
pdf_microarray/pdf_microarray.py
pdf_microarray/plot_microarray.py
pdf_microarray-1.0.1.dist-info/LICENSE
pdf_microarray-1.0.1.dist-info/METADATA
pdf_microarray-1.0.1.dist-info/WHEEL
pdf_microarray-1.0.1.dist-info/entry_points.txt
pdf_microarray-1.0.1.dist-info/RECORD
