Metadata-Version: 2.1
Name: pdf-microarray
Version: 1.0.1
Summary: A Python CLI tool designed to assist with literature research by visualizing the occurrence of words in PDF documents with a microarray format.
Home-page: https://github.com/bjorntropf/PDFMicroarray
License: GPL-3.0-or-later
Keywords: pdf,microarray
Author: Björn Tropf
Requires-Python: >=3.9,<4.0
Classifier: License :: OSI Approved :: GNU General Public License v3 or later (GPLv3+)
Classifier: Programming Language :: Python :: 3
Classifier: Programming Language :: Python :: 3.9
Classifier: Programming Language :: Python :: 3.10
Classifier: Programming Language :: Python :: 3.11
Classifier: Programming Language :: Python :: 3.12
Requires-Dist: PyMuPDF (>=1.24.2,<2.0.0)
Requires-Dist: click (>=8.1.7,<9.0.0)
Requires-Dist: matplotlib (>=3.8.4,<4.0.0)
Requires-Dist: pandas (>=2.2.2,<3.0.0)
Requires-Dist: pillow (>=10.3.0,<11.0.0)
Requires-Dist: pytesseract (>=0.3.10,<0.4.0)
Requires-Dist: seaborn (>=0.13.2,<0.14.0)
Requires-Dist: thefuzz (>=0.22.1,<0.23.0)
Project-URL: Repository, https://github.com/bjorntropf/PDFMicroarray
